Metadata-Version: 2.1
Name: aiobotocore-refreshable-credentials
Version: 1.0.4
Summary: Implements an aiobotocore.Session subclass for using aiobotocore with expiring credentials (IAM STS)
Home-page: https://github.com/aweber/aiobotocore-refreshable-credentials/
Author: Gavin M. Roy
Author-email: gavinmroy@gmail.com
License: BSD 3-Clause License
Platform: UNKNOWN
Classifier: Development Status :: 5 - Production/Stable
Classifier: Framework :: AsyncIO
Classifier: Intended Audience :: Developers
Classifier: License :: OSI Approved :: BSD License
Classifier: Natural Language :: English
Classifier: Operating System :: OS Independent
Classifier: Programming Language :: Python :: 3
Classifier: Programming Language :: Python :: 3.7
Classifier: Programming Language :: Python :: 3.8
Classifier: Programming Language :: Python :: 3.9
Classifier: Programming Language :: Python :: 3.10
Classifier: Topic :: Communications
Classifier: Topic :: Internet
Classifier: Topic :: Software Development
Classifier: Typing :: Typed
Provides-Extra: testing
License-File: LICENSE
